<?xml version="1.0" encoding="UTF-8" ?>
<!DOCTYPE mapper PUBLIC "-//mybatis.org//DTD Mapper 3.0//EN" "http://mybatis.org/dtd/mybatis-3-mapper.dtd" >
<mapper namespace="com.yscredit.pgp.mybatis.dao.DirectInfoMapper" >
  <resultMap id="BaseResultMap" type="com.yscredit.pgp.mybatis.model.DirectInfo" >
    <!--
      WARNING - @mbggenerated
      This element is automatically generated by MyBatis Generator, do not modify.
      This element was generated on Tue Dec 06 16:15:27 CST 2016.
    -->
    <id column="ID" property="id" jdbcType="INTEGER" />
    <result column="DATA_INFO_CODE" property="dataInfoCode" jdbcType="VARCHAR" />
    <result column="DEPT_CODE" property="deptCode" jdbcType="INTEGER" />
    <result column="DEPT_NAME" property="deptName" jdbcType="VARCHAR" />
  </resultMap>
  <sql id="Base_Column_List" >
    <!--
      WARNING - @mbggenerated
      This element is automatically generated by MyBatis Generator, do not modify.
      This element was generated on Tue Dec 06 16:15:27 CST 2016.
    -->
    ID, DATA_INFO_CODE, DEPT_CODE, DEPT_NAME
  </sql>
  <select id="selectByPrimaryKey" resultMap="BaseResultMap" parameterType="java.lang.Integer" >
    <!--
      WARNING - @mbggenerated
      This element is automatically generated by MyBatis Generator, do not modify.
      This element was generated on Tue Dec 06 16:15:27 CST 2016.
    -->
    select 
    <include refid="Base_Column_List" />
    from direct_info
    where ID = #{id,jdbcType=INTEGER}
  </select>
  <delete id="deleteByPrimaryKey" parameterType="java.lang.Integer" >
    <!--
      WARNING - @mbggenerated
      This element is automatically generated by MyBatis Generator, do not modify.
      This element was generated on Tue Dec 06 16:15:27 CST 2016.
    -->
    delete from direct_info
    where ID = #{id,jdbcType=INTEGER}
  </delete>
  <insert id="insert" parameterType="com.yscredit.pgp.mybatis.model.DirectInfo" >
    <!--
      WARNING - @mbggenerated
      This element is automatically generated by MyBatis Generator, do not modify.
      This element was generated on Tue Dec 06 16:15:27 CST 2016.
    -->
    insert into direct_info (ID, DATA_INFO_CODE, DEPT_CODE, 
      DEPT_NAME)
    values (#{id,jdbcType=INTEGER}, #{dataInfoCode,jdbcType=VARCHAR}, #{deptCode,jdbcType=INTEGER}, 
      #{deptName,jdbcType=VARCHAR})
  </insert>
  <insert id="insertSelective" parameterType="com.yscredit.pgp.mybatis.model.DirectInfo" >
    <!--
      WARNING - @mbggenerated
      This element is automatically generated by MyBatis Generator, do not modify.
      This element was generated on Tue Dec 06 16:15:27 CST 2016.
    -->
    insert into direct_info
    <trim prefix="(" suffix=")" suffixOverrides="," >
      <if test="id != null" >
        ID,
      </if>
      <if test="dataInfoCode != null" >
        DATA_INFO_CODE,
      </if>
      <if test="deptCode != null" >
        DEPT_CODE,
      </if>
      <if test="deptName != null" >
        DEPT_NAME,
      </if>
    </trim>
    <trim prefix="values (" suffix=")" suffixOverrides="," >
      <if test="id != null" >
        #{id,jdbcType=INTEGER},
      </if>
      <if test="dataInfoCode != null" >
        #{dataInfoCode,jdbcType=VARCHAR},
      </if>
      <if test="deptCode != null" >
        #{deptCode,jdbcType=INTEGER},
      </if>
      <if test="deptName != null" >
        #{deptName,jdbcType=VARCHAR},
      </if>
    </trim>
  </insert>
  <update id="updateByPrimaryKeySelective" parameterType="com.yscredit.pgp.mybatis.model.DirectInfo" >
    <!--
      WARNING - @mbggenerated
      This element is automatically generated by MyBatis Generator, do not modify.
      This element was generated on Tue Dec 06 16:15:27 CST 2016.
    -->
    update direct_info
    <set >
      <if test="dataInfoCode != null" >
        DATA_INFO_CODE = #{dataInfoCode,jdbcType=VARCHAR},
      </if>
      <if test="deptCode != null" >
        DEPT_CODE = #{deptCode,jdbcType=INTEGER},
      </if>
      <if test="deptName != null" >
        DEPT_NAME = #{deptName,jdbcType=VARCHAR},
      </if>
    </set>
    where ID = #{id,jdbcType=INTEGER}
  </update>
  <update id="updateByPrimaryKey" parameterType="com.yscredit.pgp.mybatis.model.DirectInfo" >
    <!--
      WARNING - @mbggenerated
      This element is automatically generated by MyBatis Generator, do not modify.
      This element was generated on Tue Dec 06 16:15:27 CST 2016.
    -->
    update direct_info
    set DATA_INFO_CODE = #{dataInfoCode,jdbcType=VARCHAR},
      DEPT_CODE = #{deptCode,jdbcType=INTEGER},
      DEPT_NAME = #{deptName,jdbcType=VARCHAR}
    where ID = #{id,jdbcType=INTEGER}
  </update>
  <select id="getDeptNameByCode" resultType="String" parameterType="java.lang.Integer" >
    select DEPT_NAME
    from direct_info
    where
    DEPT_CODE = #{deptCode}
    limit 1
  </select>

</mapper>
